rhinoinside/Rhino.Inside_v7_net48.dll
rhinoinside/Rhino.Inside_v8_net48.dll
rhinoinside/Rhino.Inside_v8_net7.0.dll
rhinoinside/Rhino.Inside_v8_net8.0.dll
rhinoinside/Rhino.Inside_v9_net48.dll
rhinoinside/Rhino.Inside_v9_net9.0.dll
rhinoinside/__init__.py
rhinoinside-0.8.2.dist-info/licenses/LICENSE
rhinoinside-0.8.2.dist-info/METADATA
rhinoinside-0.8.2.dist-info/WHEEL
rhinoinside-0.8.2.dist-info/top_level.txt
rhinoinside-0.8.2.dist-info/RECORD
