Metadata-Version: 2.4
Name: rhinoinside
Version: 0.8.2
Summary: Embed Rhino in CPython
Author-email: Robert McNeel & Associates <steve@mcneel.com>, Robert McNeel & Associates <ehsan@mcneel.com>
License: MIT
Project-URL: Homepage, https://github.com/mcneel/rhino.inside-cpython
Project-URL: Documentation, https://github.com/mcneel/rhino.inside-cpython
Project-URL: Source, https://github.com/mcneel/rhino.inside-cpython
Project-URL: Tracker, https://github.com/mcneel/rhino.inside-cpython
Classifier: Development Status :: 4 - Beta
Classifier: Intended Audience :: Developers
Classifier: License :: OSI Approved :: MIT License
Classifier: Operating System :: Microsoft :: Windows
Classifier: Programming Language :: Python
Requires-Python: >=3.7
License-File: LICENSE
Requires-Dist: pythonnet==3.0.5
Requires-Dist: dnfile==0.15.1
Dynamic: license-file
